{
  "project_info": {
    "project_number": "1066375251541",
    "firebase_url": "https://doorhubdriverapp.firebaseio.com",
    "project_id": "doorhubdriverapp",
    "storage_bucket": "doorhubdriverapp.appspot.com"
  },
  "client": [
    {
      "client_info": {
        "mobilesdk_app_id": "1:1066375251541:android:ccd6378d8ad7c34b",
        "android_client_info": {
          "package_name": "com.doorhub"
        }
      },
      "oauth_client": [
        {
          "client_id": "1066375251541-f0djrviq01320ru51d9fj33h74bn6p6m.apps.googleusercontent.com",
          "client_type": 3
        }
      ],
      "api_key": [
        {
          "current_key": "AIzaSyBLv9PIj19Rs-guSviF_tkjEvZT29o_BpQ"
        }
      ],
      "services": {
        "appinvite_service": {
          "other_platform_oauth_client": [
            {
              "client_id": "1066375251541-f0djrviq01320ru51d9fj33h74bn6p6m.apps.googleusercontent.com",
              "client_type": 3
            },
            {
              "client_id": "1066375251541-r5q9r4rgmqv019inb9m0a6es0mnacof5.apps.googleusercontent.com",
              "client_type": 2,
              "ios_info": {
                "bundle_id": "org.reactjs.native.example.pushNotificationss"
              }
            }
          ]
        }
      }
    },
    {
      "client_info": {
        "mobilesdk_app_id": "1:1066375251541:android:f9ad8eb458db81799a76dc",
        "android_client_info": {
          "package_name": "com.pushnotifications"
        }
      },
      "oauth_client": [
        {
          "client_id": "1066375251541-f0djrviq01320ru51d9fj33h74bn6p6m.apps.googleusercontent.com",
          "client_type": 3
        }
      ],
      "api_key": [
        {
          "current_key": "AIzaSyBLv9PIj19Rs-guSviF_tkjEvZT29o_BpQ"
        }
      ],
      "services": {
        "appinvite_service": {
          "other_platform_oauth_client": [
            {
              "client_id": "1066375251541-f0djrviq01320ru51d9fj33h74bn6p6m.apps.googleusercontent.com",
              "client_type": 3
            },
            {
              "client_id": "1066375251541-r5q9r4rgmqv019inb9m0a6es0mnacof5.apps.googleusercontent.com",
              "client_type": 2,
              "ios_info": {
                "bundle_id": "org.reactjs.native.example.pushNotificationss"
              }
            }
          ]
        }
      }
    }
  ],
  "configuration_version": "1"
}